{
  "pTypeB/pTypeB.kicad_pcb": {
    "selAnchor": "R1",
    "enabledDict": {
      "344ae87c-6489-4bd0-b0bd-ddf77e543a2a": true
    }
  },
  "nType/nType.kicad_pcb": {
    "selAnchor": "D1",
    "enabledDict": {
      "6135ce1c-b744-4b77-ae78-eb08171e0e4b": true
    }
  },
  "nTypeA/nTypeA.kicad_pcb": {
    "selAnchor": "D1",
    "enabledDict": {
      "86bc2818-09a8-4e11-a616-4bcb784038b9": true
    }
  },
  "pTypeA/pTypeA.kicad_pcb": {
    "selAnchor": "Q1",
    "enabledDict": {
      "de9269f9-2f9f-42b3-9740-982aa93457ec": true
    }
  }
}